manim_ext_movi/__init__.py
manim_ext_movi/background/__init__.py
manim_ext_movi/background/simple_shapes.py
manim_ext_movi/creatures/__init__.py
manim_ext_movi/creatures/creature_lambda.py
manim_ext_movi/creatures/creature_unity.py
manim_ext_movi/creatures/assets/lambda.svg
manim_ext_movi/creatures/assets/unity.svg
manim_ext_movi/scenes/creature_lambda.py
manim_ext_movi/scenes/creature_unity.py
manim_ext_movi-0.0.3.dist-info/LICENSE.txt
manim_ext_movi-0.0.3.dist-info/METADATA
manim_ext_movi-0.0.3.dist-info/WHEEL
manim_ext_movi-0.0.3.dist-info/top_level.txt
manim_ext_movi-0.0.3.dist-info/RECORD
